radial/__init__.py
radial/http_client.py
radial-0.1.0.dist-info/LICENSE
radial-0.1.0.dist-info/WHEEL
radial-0.1.0.dist-info/METADATA
radial-0.1.0.dist-info/RECORD
