Metadata-Version: 2.1
Name: radial
Version: 0.1.0
Summary: An intiutive interface for your requests in seconds
Author: Shiv
Author-email: hello@shivs.me
Requires-Python: >=3.8,<4.0
Classifier: Programming Language :: Python :: 3
Classifier: Programming Language :: Python :: 3.8
Classifier: Programming Language :: Python :: 3.9
Classifier: Programming Language :: Python :: 3.10
Classifier: Programming Language :: Python :: 3.11
Requires-Dist: requests (>=2.28.1,<3.0.0)
